{
  "id": "ielts-general-mock-1",
  "mockNumber": 1,
  "title": "IELTS General Training Mock Test 1",
  "testBrand": "ielts",
  "type": "general",
  "description": "Complete IELTS General Training test with all 4 skills",
  "xpReward": 5000,
  "tier": "bronze",
  "instructions": "Read the instructions for each part of the paper carefully. Answer all the questions. Write your answers in the answer sheet. You must complete the answer sheet within the time limit. At the end of the test, hand in both this question paper and your answer sheet.",
  "vocabulary": {
    "id": "vocab-general-1",
    "title": "Test Vocabulary",
    "level": "B2",
    "words": [
      {
        "term": "approximately",
        "hu": "körülbelül",
        "definition": "About or roughly",
        "example": "The Earth formed approximately 4.5 billion years ago."
      },
      {
        "term": "consist",
        "hu": "áll",
        "definition": "To be composed or made up of",
        "example": "The Solar System consists of eight planets."
      },
      {
        "term": "surface",
        "hu": "felszín",
        "definition": "The outside or top layer",
        "example": "The Earth's surface is 71% water."
      },
      {
        "term": "originates",
        "hu": "ered",
        "definition": "To come from a source",
        "example": "The idea of months originated from the moon."
      },
      {
        "term": "habitat",
        "hu": "élöhely",
        "definition": "A natural home for organisms",
        "example": "The biosphere includes all habitats on Earth."
      },
      {
        "term": "convert",
        "hu": "átalakít",
        "definition": "To change from one form to another",
        "example": "Cyanobacteria convert sunlight to oxygen."
      },
      {
        "term": "diameter",
        "hu": "átmérö",
        "definition": "The distance across a circle",
        "example": "The Earth has a diameter of about 12,742 km."
      },
      {
        "term": "rotate",
        "hu": "forog",
        "definition": "To spin on an axis",
        "example": "The Earth rotates on its axis once a day."
      },
      {
        "term": "extensive",
        "hu": "kiterjedt",
        "definition": "Covering a large area",
        "example": "Advantage Sales & Marketing offers extensive services."
      },
      {
        "term": "flexible",
        "hu": "rugalmas",
        "definition": "Able to adapt",
        "example": "Chipotle offers a flexible work schedule."
      },
      {
        "term": "progressive",
        "hu": "progresszív",
        "definition": "Forward-thinking",
        "example": "The Vitamin Shoppe has progressive policies."
      },
      {
        "term": "compassionate",
        "hu": "áldozatos",
        "definition": "Showing care and concern",
        "example": "PSA Healthcare provides compassionate care."
      },
      {
        "term": "candidate",
        "hu": "jelölt",
        "definition": "A person being considered for a position",
        "example": "Candidates must have experience."
      },
      {
        "term": "opportunity",
        "hu": "lehetöség",
        "definition": "A chance for progress",
        "example": "There are room for advancement opportunities."
      },
      {
        "term": "comprehensive",
        "hu": "közérthetö",
        "definition": "Complete and thorough",
        "example": "PSA Healthcare provides comprehensive services."
      },
      {
        "term": "emergency",
        "hu": "vész",
        "definition": "A serious, unexpected situation",
        "example": "Fire drills prepare you for emergencies."
      },
      {
        "term": "evacuate",
        "hu": "elhagy",
        "definition": "To leave a dangerous place",
        "example": "You must evacuate during a fire."
      },
      {
        "term": "hazard",
        "hu": "veszély",
        "definition": "A danger or risk",
        "example": "Fire is a major hazard."
      },
      {
        "term": "respond",
        "hu": "válaszol",
        "definition": "To react to something",
        "example": "People must respond quickly to fire alarms."
      },
      {
        "term": "precaution",
        "hu": "elözmély",
        "definition": "A measure taken to prevent something",
        "example": "Fire drills are an important precaution."
      }
    ]
  },
  "reading": {
    "title": "General Training Reading Mock 1 - All Question Types",
    "time": 60,
    "sections": [
      {
        "id": "s1",
        "section": 1,
        "title": "Reading Passage 1: The Earth",
        "description": "Questions 1-14 - Types: Matching Choice, MCQ, Trinary (True/False), Headings Match",
        "passages": [
          {
            "id": "p1",
            "subtitle": "Reading Passage 1",
            "title": "The Earth",
            "type": "ielts-complex",
            "vocabList": [
              {
                "term": "approximately",
                "hu": "körülbelül",
                "definition": "About or roughly"
              },
              {
                "term": "surface",
                "hu": "felszín",
                "definition": "The outside or top layer"
              },
              {
                "term": "habitat",
                "hu": "élöhely",
                "definition": "A natural home for organisms"
              },
              {
                "term": "rotate",
                "hu": "forog",
                "definition": "To spin on an axis"
              }
            ],
            "content": [
              {
                "id": "A",
                "text": "The Earth is the third planet from the Sun and it is the only planet known to have life on it. The Earth formed around 4.5 billion years ago. It is one of four rocky planets on the inside of the Solar System. The other three are Mercury, Venus, and Mars."
              },
              {
                "id": "B",
                "text": "The large mass of the Sun makes the Earth move around it, just as the mass of the Earth makes the Moon move around it. The Earth also turns round in space, so different parts face the Sun at different times. The Earth goes around the Sun once (one 'year') for every 365¼ times it turns all the way around (one 'day')."
              },
              {
                "id": "C",
                "text": "The Moon goes around the Earth about every 27⅓ days, and reflects light from the Sun. As the Earth goes round the Sun at the same time, the changing light of the Moon takes about 29½ days to go from dark to bright to dark again. That is where the idea of 'month' came from. However, now most months have 30 or 31 days so they fit into one year."
              },
              {
                "id": "D",
                "text": "The Earth is the only planet in our Solar System that has a large amount of liquid water. About 71% of the surface of the Earth is covered by oceans. Because of this, it is sometimes called the 'Blue Planet'."
              },
              {
                "id": "E",
                "text": "Because of its water, the Earth is home to millions of species of plants and animals. The things that live on Earth have changed its surface greatly. For example, early cyanobacteria changed the air and gave it oxygen. The living part of the Earth's surface is called the 'biosphere'."
              },
              {
                "id": "F",
                "text": "The Earth is part of the eight planets and many thousands of small bodies that move around the Sun as its Solar System. The Solar System is moving through the Orion Arm of the Milky Way Galaxy now, and will be for about the next 10,000 years."
              },
              {
                "id": "G",
                "text": "The Earth is generally 150,000,000 kilometers or 93,000,000 miles away from the Sun (this distance is named an 'Astronomical Unit'). The Earth moves along its way at an average speed of about 30 km or 19 mi a second. The Earth turns all the way around about 365¼ times in the time it takes for the Earth to go all the way around the Sun. To make up this extra bit of a day every year, an additional day is used every four years. This is named a 'leap year'."
              },
              {
                "id": "H",
                "text": "The Moon goes around the Earth at an average distance of 400,000 kilometers (250,000 mi). It is locked to Earth, so that it always has the same half facing the Earth; the other half is called the 'dark side of the Moon'."
              }
            ],
            "subTasks": [
              {
                "type": "matching-info",
                "instruction": "Which paragraph (A-H) contains the following information?",
                "questions": [
                  {
                    "id": "1",
                    "text": "How long it takes the Earth to go around the Sun",
                    "answer": "B"
                  },
                  {
                    "id": "2",
                    "text": "How the Moon affects the calendar",
                    "answer": "C"
                  },
                  {
                    "id": "3",
                    "text": "The reason Earth is called the Blue Planet",
                    "answer": "D"
                  }
                ]
              },
              {
                "type": "mcq",
                "instruction": "Choose the correct answer",
                "questions": [
                  {
                    "id": "4",
                    "text": "What percentage of Earth's surface is water?",
                    "options": [
                      "51%",
                      "61%",
                      "71%",
                      "81%"
                    ],
                    "answer": "71%"
                  },
                  {
                    "id": "5",
                    "text": "What is the 'biosphere'?",
                    "options": [
                      "The atmosphere",
                      "The part where life exists",
                      "The oceans",
                      "The core"
                    ],
                    "answer": "The part where life exists"
                  }
                ]
              },
              {
                "type": "trinary",
                "instruction": "Write TRUE, FALSE or NOT GIVEN.",
                "questions": [
                  {
                    "id": "6",
                    "text": "Venus is a rocky planet.",
                    "answer": "TRUE"
                  },
                  {
                    "id": "7",
                    "text": "The Sun moves around the Earth.",
                    "answer": "FALSE"
                  },
                  {
                    "id": "8",
                    "text": "Cyanobacteria produced oxygen.",
                    "answer": "TRUE"
                  }
                ]
              },
              {
                "type": "heading-match",
                "instruction": "Choose the correct heading for each paragraph.",
                "questions": [
                  {
                    "id": "9",
                    "text": "Paragraph A",
                    "answer": 3
                  },
                  {
                    "id": "10",
                    "text": "Paragraph B",
                    "answer": 4
                  },
                  {
                    "id": "11",
                    "text": "Paragraph C",
                    "answer": 5
                  }
                ],
                "headings": [
                  "The Earth's position in the Solar System",
                  "The Moon's orbit and phases",
                  "Water and the Blue Planet",
                  "Formation and age of the Earth",
                  "Earth's movement and the calendar",
                  "Origin of the concept of months",
                  "The biosphere and life on Earth",
                  "Distance from the Sun",
                  "The Moon's characteristics"
                ]
              }
            ]
          }
        ]
      },
      {
        "id": "s2",
        "section": 2,
        "title": "Reading Passage 2: Company Profiles",
        "description": "Reading Passage 2",
        "passages": [
          {
            "id": "p2",
            "title": "Company Profiles",
            "subtitle": "Reading Passage 2",
            "type": "ielts-complex",
            "content": [
              { "id": "A", "text": "The Vitamin Shoppe has 1,946 part-time openings. This New Jersey-based retailer of nutritional supplements also operates stores in Canada under the name 'VitaPath'. The company provides approximately 8,000 different products through its retail stores and over 20,000 through its online websites. Employees have noted good growth opportunities, progressive policies, and above-average pay." },
              { "id": "B", "text": "Chipotle currently offers 1,553 part-time openings. Known for using organic meats throughout its more than 1,500 restaurants, the chain has grown to 37,000 employees since its founding in 1993. While the schedule is described as super flexible, employees mention that the work is fast-paced and requires a lot of effort." },
              { "id": "C", "text": "Advantage Sales & Marketing has 1,742 part-time openings. They provide outsourced sales and marketing services to major manufacturers like Johnson & Johnson and Unilever. With more than 65 offices in the US and Canada, the company is recognized for its ability to adapt to market changes and offering a well-thought-out, flexible schedule." },
              { "id": "D", "text": "Universal Protection Service is one of the largest providers of security services in the U.S., with 1,219 part-time openings. They offer security solutions for a variety of sectors, including airports and healthcare facilities. Many employees highlight the room for advancement and competitive pay compared to other security firms." },
              { "id": "E", "text": "PSA Healthcare, also known as Pediatric Services of America, has 1,295 part-time openings. Headquartered in Atlanta, they provide comprehensive home health services. Employees appreciate the ability to provide compassionate one-on-one care and the flexibility offered by supervisors regarding time-off requests." }
            ],
            "subTasks": [
              {
                "type": "short-answer",
                "instruction": "Short Answer Questions: Write NO MORE THAN THREE WORDS.",
                "questions": [
                  {
                    "id": "12",
                    "text": "What industry does ASM serve?",
                    "answer": "retail"
                  },
                  {
                    "id": "13",
                    "text": "What is Chipotle known for?",
                    "answer": "fresh ingredients"
                  },
                  {
                    "id": "14",
                    "text": "What does Vitamin Shoppe sell?",
                    "answer": "nutritional supplements"
                  }
                ]
              },
              {
                "id": "company-descriptions-match",
                "type": "sentence-matching",        
                "options": [
                  "good growth opportunities and above-average pay.",
                  "The company has flexible schedules but requires a lot of effort.",
                  "This company provides outsourced sales and marketing services and offers a flexible schedule.",
                  "It is one of the largest security service providers and offers competitive pay.",
                  "Employees appreciate the ability to provide one-on-one care and flexible time-off."
                ],
                "questions": [ 
                  { "id": 15, "text": "This company has", "answer": "good growth opportunities and above-average pay." },
                  { "id": 16, "text": "Chipotle", "answer": "The company has flexible schedules but requires a lot of effort." },
                  { "id": 17, "text": "Advantage Sales & Marketing", "answer": "This company provides outsourced sales and marketing services and offers a flexible schedule." },
                  { "id": 18, "text": "Universal Protection Service", "answer": "It is one of the largest security service providers and offers competitive pay." },
                  { "id": 19, "text": "PSA Healthcare", "answer": "Employees appreciate the ability to provide one-on-one care and flexible time-off." }
                ]
              },
              {
                "type": "sentence-complete",
                "instruction": "Complete the sentences. Write NO MORE THAN TWO WORDS for each answer.",
                "questions": [
                  { "id": "19", "text": "The Vitamin Shoppe offers approximately ______ different products.", "answer": "8000", "wordLimit": 2 },
                  { "id": "20", "text": "Chipotle was founded in ______.", "answer": "1993", "wordLimit": 2 },
                  { "id": "21", "text": "ASM has more than ______ offices in the US and Canada.", "answer": "65", "wordLimit": 2 },
                  { "id": "22", "text": "PSA Healthcare is headquartered in ______.", "answer": "Atlanta", "wordLimit": 2 }
                ]
              },
              {
                "type": "trinary",
                "instruction": "Write YES, NO or NOT GIVEN.",
                "questions": [
                  {
                    "id": "23",
                    "text": "The Vitamin Shoppe pays above-average wages.",
                    "answer": "YES"
                  },
                  {
                    "id": "24",
                    "text": "Chipotle employees find the work relaxing.",
                    "answer": "NO"
                  },
                  {
                    "id": "25",
                    "text": "All companies offer flexible schedules.",
                    "answer": "NOT GIVEN"
                  }
                ]
              }
            ]
          }
        ]
      },
      {
        "id": "s3",
        "section": 3,
        "title": "Reading Passage 3: Fire Safety",
        "description": "Questions 29-40 - Types: Flow-chart, Sentence Matching, Diagram Label, Short Answer",
        "passages": [
          {
            "id": "p3",
            "title": "Fire Safety",
            "subtitle": "Reading Passage 3",
            "type": "ielts-complex",
            "content": [
              { "id": "A", "text": "Fire drills are a big part of being safe in school: They prepare you for what you need to do in case of a fire. But what if there was a fire where you live? Would you know what to do? Talking about fires can be scary because no one likes to think about people getting hurt or their things getting burned. But you can feel less worried if you are prepared." },
              { "id": "B", "text": "It's a good idea for families to talk about what they would do to escape a fire. Different families will have different strategies. Some kids live in one-story houses and other kids live in tall buildings. You'll want to talk about escape plans and escape routes, so let's start there." },
              { "id": "C", "text": "An escape plan can help every member of a family get out of a burning house. The idea is to get outside quickly and safely. Smoke from a fire can make it hard to see where things are, so it's important to learn and remember the different ways out of your home. How many exits are there? How do you get to them from your room? It's a good idea to have your family draw a map of the escape plan. It's possible one way out could be blocked by fire or smoke, so you'll want to know where other ones are. And if you live in an apartment building, you'll want to know the best way to the stairwell or other emergency exits." },
              { "id": "D", "text": "If you're in a room with the door closed when the fire breaks out, you need to take a few extra steps: Check to see if there's heat or smoke coming in the cracks around the door. (You're checking to see if there's fire on the other side.) If you see smoke coming under the door — don't open the door! If you don't see smoke — touch the door. If the door is hot or very warm — don't open the door! If you don't see smoke — and the door is not hot — then use your fingers to lightly touch the doorknob. If the doorknob is hot or very warm — don't open the door! If the doorknob feels cool, and you can't see any smoke around the door, you can open the door very carefully and slowly. When you open the door, if you feel a burst of heat or smoke pours into the room, quickly shut the door and make sure it is really closed. If there's no smoke or heat when you open the door, go toward your escape route exit." }
            ],
            "subTasks": [
              {
                "type": "flowchart",
                "instruction": "Type 9 - Flow-chart Completion: Complete the PASS method. Write ONE WORD ONLY.",
                "flowchart": {
                  "text": "The PASS method is a simple four-step technique for using a fire extinguisher. It stands for Pull, Aim, Squeeze, and Sweep. This method helps people remember the correct sequence of actions when using a fire extinguisher to put out a small fire.",
                  "caption": "PASS Fire Extinguisher Method"
                },
                "questions": [
                  {
                    "id": "26",
                    "text": "Step 1: ______ the pin.",
                    "answer": "Pull"
                  },
                  {
                    "id": "27",
                    "text": "Step 2: ______ at the base.",
                    "answer": "Aim"
                  },
                  {
                    "id": "28",
                    "text": "Step 3: ______ the handle.",
                    "answer": "Squeeze"
                  },
                  {
                    "id": "29",
                    "text": "Step 4: ______ from side to side.",
                    "answer": "Sweep"
                  }
                ]
              },
              {
                "type": "sentence-matching",
                "instruction": " Match the sentence beginnings (A-F) with the correct endings (i-vi).",
                "questions": [
                  { "id": "30", "text": "Fire drills are important because", "answer": "they prepare you for what to do in case of fire" },
                  { "id": "31", "text": "Families should discuss", "answer": "their escape plans and routes" },
                  { "id": "32", "text": "An escape plan helps", "answer": "every family member get out safely" }
                ],
                "options": [
                  "to see if there's fire on the other side of the door",
                  "they prepare you for what to do in case of fire",
                  "their escape plans and routes",
                  "you should know the best way to the stairwell",
                  "every family member get out safely",
                  "to see where things are"
                ]
              },
              {
                "type": "diagram-label",
                "instruction": "Type 10 - Diagram Label Completion: Label the fire escape plan. Write the correct label for each letter.",
                "wordLimit": 1,
                "labels": [
                  {
                    "id": "Bedroom",
                    "letter": "A",
                    "answer": "Bedroom"
                  },
                  {
                    "id": "Door",
                    "letter": "B",
                    "answer": "Door"
                  },
                  {
                    "id": "Hallway",
                    "letter": "C",
                    "answer": "Hallway"
                  },
                  {
                    "id": "Stairwell",
                    "letter": "D",
                    "answer": "Stairwell"
                  }
                ],
                "diagram": {
                  "text": "The building has a main entrance on the ground floor leading to a reception area. The stairwell is located in the center of the building, providing access to all floors. On the second floor, there are two bedrooms: one on the east side and one on the west side. Each bedroom has a door opening to a shared hallway. The hallway connects to the stairwell and also leads to a fire exit at the rear of the building.",
                  "src": "/images/city-diagram1.png",
                  "alt": "Fire escape plan diagram showing building layout with labeled areas",
                  "caption": "Fire Escape Plan - Write the correct label for each letter",
                  "width": "100%",
                  "height": "400px"
                },
                "options": [
                  "A",
                  "B",
                  "C",
                  "D",
                  "E",
                  "F"
                ]
              },
              {
                "type": "short-answer",
                "instruction": "Type 11 - Short Answer Questions: Answer the questions using NO MORE THAN THREE WORDS.",
                "questions": [
                  {
                    "id": "37",
                    "text": "What type of equipment should be regularly inspected?",
                    "answer": "electrical equipment",
                    "wordLimit": 3
                  },
                  {
                    "id": "38",
                    "text": "What materials should be kept away from heat sources?",
                    "answer": "flammable materials",
                    "wordLimit": 3
                  },
                  {
                    "id": "39",
                    "text": "How often should smoke detector batteries be changed?",
                    "answer": "once a year",
                    "wordLimit": 3
                  },
                  {
                    "id": "40",
                    "text": "What should never be used during a fire?",
                    "answer": "elevators",
                    "wordLimit": 3
                  }
                ]
              }
            ]
          }
        ]
      }
    ]
  },
  "writing": {
    "title": "Writing",
    "time": 60,
    "sections": [
      {
        "id": "w-m1-t1",
        "taskType": 1,
        "title": "Task 1: Letter",
        "subtitle": "Part 1: Writing",
        "instruction": "You should spend about 20 minutes on this task. Write at least 150 words.",
        "targetWords": 150,
        "xp": 250,
        "prompt": "You recently moved to a new city. Write a letter to a friend telling them about your new home and inviting them to visit.",
        "bullets": [
          "Describe your new home",
          "Explain what you like about the area",
          "Suggest when they could visit"
        ],
        "type": "letter"
      },
      {
        "id": "w-m1-t2",
        "taskType": 2,
        "title": "Task 2: Essay",
        "subtitle": "Part 2: Writing",
        "instruction": "You should spend about 40 minutes on this task. Write at least 250 words.",
        "targetWords": 250,
        "xp": 500,
        "prompt": "Some people believe that unpaid community service should be a compulsory part of high school programs. To what extent do you agree or disagree?",
        "bullets": [
          "Give reasons for your answer",
          "Include relevant examples from your knowledge or experience"
        ],
        "type": "essay"
      }
    ]
  },
  "speaking": {
    "title": "Speaking",
    "time": 15,
    "parts": [
      {
        "id": "part1",
        "title": "Introduction and Interview",
        "subtitle": "Part 1: Speaking",
        "type": "interview",
        "duration": "4-5 minutes",
        "instruction": "Answer the examiner's questions about familiar topics. Speak naturally and give full answers.",
        "topics": [
          {
            "topic": "Your Home Town or Village",
            "questions": [
              {
                "id": "p1q1",
                "text": "What kind of place is it?"
              },
              {
                "id": "p1q2",
                "text": "What's the most interesting part of your town/village?"
              },
              {
                "id": "p1q3",
                "text": "What kind of jobs do the people in your town/village do?"
              },
              {
                "id": "p1q4",
                "text": "Would you say it's a good place to live? (Why?)"
              }
            ]
          }
        ]
      },
      {
        "id": "part2",
        "title": "Long Turn",
        "subtitle": "Part 2: Speaking",
        "type": "long-turn",
        "duration": "3-4 minutes",
        "instruction": "You will have 1 minute to prepare, then speak for 1-2 minutes on the topic.",
        "topicCard": {
          "id": "task1",
          "topic": "Describe something valuable that you own.",
          "description": "You should say:",
          "bullets": [
            "what it is",
            "how you got it",
            "what you use it for",
            "explain why it is valuable to you"
          ],
          "roundingQuestions": [
            {
              "id": "r1",
              "text": "Is it valuable in terms of money?"
            },
            {
              "id": "r2",
              "text": "Would it be easy to replace?"
            }
          ]
        }
      },
      {
        "id": "part3",
        "title": "Discussion",
        "subtitle": "Part 3: Speaking",
        "type": "discussion",
        "duration": "4-5 minutes",
        "instruction": "Discuss more abstract topics related to Part 2. Give reasons and examples.",
        "topics": [
          {
            "topic": "Possessions and Value",
            "questions": [
              {
                "id": "p3q1",
                "text": "In general, what do you consider to be valuable possessions?"
              },
              {
                "id": "p3q2",
                "text": "Do you think people place too much importance on material possessions?"
              },
              {
                "id": "p3q3",
                "text": "How do advertisements influence what people consider valuable?"
              },
              {
                "id": "p3q4",
                "text": "Do you think the things people value change as they get older?"
              }
            ]
          }
        ]
      }
    ]
  },
  "listening": {
    "title": "Listening",
    "time": 30,
    "instructions": "You will hear a number of different recordings and you will have to answer questions on what you hear. There will be time for you to read the instructions and questions, and you will have a chance to check your work. All the recordings will be played once only. The test is in 4 parts. At the end of the test, you will be given 10 minutes to transfer your answers to the answer sheet.",
    "sections": [
      {
        "id": "part1",
        "part": 1,
        "title": "Booking a Holiday Cottage",
        "subtitle": "Part 1: Listening",
        "description": "You will hear a conversation between a travel agent and a customer who wants to book a holiday cottage. First, you have some time to look at questions 1-10.",
        "transcript": "Travel Agent: Good morning, Lake District Holidays. How can I help you?\n\nCustomer: Good morning. I'm interested in booking a holiday cottage in the Lake District. Could you give me some information?\n\nTravel Agent: Of course. May I take your name?\n\nCustomer: Yes, it's Sarah Mitchell. S-A-R-A-H M-I-T-C-H-E-L-L.\n\nTravel Agent: Thank you, Ms Mitchell. And may I have your contact telephone number?\n\nCustomer: It's 07788 456321.\n\nTravel Agent: 07788 456321. Got it. Now, what location in the Lake District are you looking for?\n\nCustomer: I'd preferably like somewhere near Windermere if possible.\n\nTravel Agent: Windermere is a beautiful area. How many people will be staying at the cottage?\n\nCustomer: There will be four adults and two children.\n\nTravel Agent: Four adults and two children. And do you have a maximum budget per week?\n\nCustomer: We'd prefer to stay under 800 pounds per week if we can.\n\nTravel Agent: Under 800 pounds. Any particular facilities you require?\n\nCustomer: A garden is important as the children like to play outside.\n\nTravel Agent: A garden, noted. When were you thinking of arriving?\n\nCustomer: We're hoping to arrive on the 15th of July.\n\nTravel Agent: 15th July. Is there anything else that's important to you?\n\nCustomer: Well, we're bringing the car, so parking is a main concern. I'd like to make sure there's adequate parking available.\n\nTravel Agent: I understand. We have several properties with good parking facilities. Would you like me to send you a brochure with details of suitable properties?\n\nCustomer: Yes, that would be very helpful.\n\nTravel Agent: I'll put one in the post to you today. Thank you for calling, Ms Mitchell.\n\nCustomer: Thank you. Goodbye.",
        "audioUrl": "https://www.soundhelix.com/examples/mp3/SoundHelix-Song-1.mp3",
        "context": "Conversation between two speakers - social situation",
        "type": "LISTENING",
        "skill": "listening",
        "subTasks": [
          {
            "type": "short-answer",
            "instruction": "Complete the form below. Write NO MORE THAN TWO WORDS AND/OR A NUMBER for each answer.",
            "questions": [
              {
                "id": 1,
                "text": "Customer name:",
                "answer": "Sarah Mitchell",
                "wordLimit": 2,
                "allowNumber": true
              },
              {
                "id": 2,
                "text": "Contact telephone:",
                "answer": "07788 456321",
                "wordLimit": 1,
                "allowNumber": true
              },
              {
                "id": 3,
                "text": "Preferred location:",
                "answer": "Lake District",
                "wordLimit": 2,
                "allowNumber": false
              },
              {
                "id": 4,
                "text": "Number of adults:",
                "answer": "4",
                "wordLimit": 1,
                "allowNumber": true
              },
              {
                "id": 5,
                "text": "Number of children:",
                "answer": "2",
                "wordLimit": 1,
                "allowNumber": true
              }
            ]
          },
          {
            "type": "notes-completion",
            "instruction": "Complete the booking notes below. Write NO MORE THAN TWO WORDS AND/OR A NUMBER for each answer.",
            "wordLimit": 2,
            "notes": [
              {
                "heading": "Customer Requirements",
                "items": [
                  { "id": "6", "type": "gap", "label": "Maximum budget per week:", "answer": "800 pounds" },
                  { "id": "7", "type": "gap", "label": "Required facility:", "answer": "garden" },
                  { "id": "8", "type": "gap", "label": "Arrival date:", "answer": "15th July" },
                  { "id": "9", "type": "gap", "label": "Main concern:", "answer": "parking" },
                  { "id": "10", "type": "gap", "label": "Request:", "answer": "brochure" }
                ]
              }
            ]
          }
        ]
      },
      {
        "id": "part2",
        "part": 2,
        "title": "Tour of a Museum Complex",
        "subtitle": "Part 2: Listening",
        "description": "You will hear a guide giving a tour of a museum complex. First, you have some time to look at questions 11-20.",
        "transcript": "Guide: Good afternoon, everyone, and welcome to the Riverside Museum Complex. My name is Emma, and I'll be your guide today. Before we begin our tour, let me give you an overview of what you'll see.\n\nThis building was originally a private residence, built in 1890 by the wealthy Thompson family. In 1952, it was donated to the city and converted into a museum. The building has been carefully restored to maintain its original Victorian features while housing our modern exhibits.\n\nNow, let's start with the ground floor. As you can see on your map, the Ticket Office is at the entrance, marked with the letter A. Once you've purchased your tickets, you can either head straight to the Main Exhibition Hall, which is location C in the centre of the building, or stop by our Café, which is marked D, for a refreshment before your tour.\n\nThe Main Exhibition Hall houses our permanent collection, which focuses primarily on local history. You'll find displays covering the region's industrial heritage, from the textile mills of the 18th century to the railway expansion in the 1850s. We also have rotating exhibitions that change every three months.\n\nIf you continue down this corridor, you'll reach the Gift Shop, marked with F. It's open throughout the day and stocks a wonderful range of locally produced crafts and souvenirs.\n\nFor families with children, I'm pleased to tell you about our Children's Activity Centre, which is at location H on the upper floor. This hands-on discovery area is perfect for kids aged 5 to 12, where they can dress up in period costumes and try traditional crafts.\n\nNow, regarding our dining facilities: our restaurant can serve up to 200 people at any one time, and we recommend booking if you're planning to eat here during peak hours. The restaurant is open from 11 am to 4 pm daily.\n\nFor those of you who are museum members, I'm happy to announce that guided tours are completely free for members. We offer three tours daily, at 11 am, 2 pm, and 3:30 pm, each lasting approximately one hour. Non-members can join a tour for £5 per person.\n\nParking is available in the car park behind the museum, with 150 spaces. Members park free of charge. If you have any questions, please don't hesitate to ask. Enjoy your visit!",
        "audioUrl": "https://www.soundhelix.com/examples/mp3/SoundHelix-Song-2.mp3",
        "context": "Monologue - information about local facilities",
        "type": "LISTENING",
        "skill": "listening",
        "subTasks": [
          {
            "id": 11,
            "type": "diagram-label",
            "instruction": "Label the map below. Write the correct letter, A-H, next to Questions 11-15.",
            "labels": [
              {
                "id": "11",
                "text": "Ticket Office",
                "answer": "A"
              },
              {
                "id": "12",
                "text": "Café",
                "answer": "D"
              },
              {
                "id": "13",
                "text": "Gift Shop",
                "answer": "F"
              },
              {
                "id": "14",
                "text": "Main Exhibition Hall",
                "answer": "C"
              },
              {
                "id": "15",
                "text": "Children's Activity Centre",
                "answer": "H"
              }
            ],
            "diagram": {
                "src": "/images/building-diagram1.png",
                "alt": "Museum map"
              },
            "wordLimit": 1,
            "options": [
              "A",
              "B",
              "C",
              "D",
              "E",
              "F",
              "G",
              "H"
            ]
          },
          {
                "type": "mcq",
                "instruction": "Choose the correct answer",
                "questions": [
                  {
                  "id": 16,
                  "text": "The museum was originally built as a",
                  "options": [
                    "a private residence",
                    "a government building",
                    "a factory"
                  ],
                    "answer": "a private residence"
                  },
                  {
                    "id": 17,
                    "text": "The museum's collection focuses mainly on",
                    "options": [
                      "ancient artefacts",
                      "local history",
                      "modern art"
                    ],
                  "answer": "local history"
                  },
                  {
            "id": 18,
            "text": "The guided tours last approximately",
            "options": [
              "45 minutes",
              "1 hour",
              "90 minutes"
            ],
            "answer": "1 hour"
          },
          {
            "id": 19,
            "text": "The restaurant can serve",
            "options": [
              "50 people",
              "100 people",
              "200 people"
            ],
            "answer": "200 people"
          },
          {
            "id": 20,
            "text": "What is free for members?",
            "options": [
              "parking",
              "guides",
              "coffee"
            ],
            "answer": "guides"
           }
          ]
         }
        ]
      },
      {
        "id": "part3",
        "part": 3,
        "title": "Discussion about University Course",
        "subtitle": "Part 3: Listening",
        "description": "You will hear a discussion between a student and an academic advisor. First, you have some time to look at questions 21-30.",
        "transcript": "Advisor: Hello, James. Please, have a seat. I've been looking through your request form. You want to discuss your final year assignment, is that right?\n\nStudent: Yes, thank you for seeing me, Dr. Roberts. I'm a bit worried about it, to be honest. It's for the Business Strategy module.\n\nAdvisor: I see. You're studying Business, correct?\n\nStudent: That's right. I'm in my final year, specializing in Management.\n\nAdvisor: Good. Now, I can see here that you've chosen to write about competitive strategy in the retail sector. That's an interesting topic. What seems to be the problem?\n\nStudent: Well, I'm concerned about the deadline. The form says it's due next week, but I thought we had more time.\n\nAdvisor: Let me check... Yes, the deadline is indeed in one week's time - that's the 15th of March. The assignment brief was clear about this from the beginning of the semester.\n\nStudent: I see. I must have misread the dates. So it's due in one week, not two. That's very soon!\n\nAdvisor: It is, but it's still doable. I understand you're also working part-time, which can make things challenging. Let's discuss how you can manage this. First, have you started any research?\n\nStudent: I've done some initial reading, but not much. I know I'll need to use the university's online databases for academic sources.\n\nAdvisor: That's a good start. Yes, I'd strongly recommend using our online databases - you'll find plenty of peer-reviewed articles there. For this assignment, you'll need a minimum of 15 sources in your bibliography.\n\nStudent: Fifteen! That's a lot.\n\nAdvisor: It is, but quality matters more than quantity. Make sure they're recent - preferably published within the last five years. Now, regarding the format, are you familiar with APA style?\n\nStudent: I think so. Is that the one with the author-date in-text citations?\n\nAdvisor: Exactly. APA style is required for this module. Also, the essay must be a minimum of 3000 words. I recommend using Word for formatting - it has excellent referencing tools that will save you time.\n\nStudent: Good to know. Dr. Roberts, I was wondering - would you be able to look at a first draft before I submit?\n\nAdvisor: I'm afraid I won't have time to review drafts - I'm away at a conference next week. However, I can recommend that you submit your draft to the peer review system. There should be an external examiner available to give you feedback. Alternatively, you could ask some fellow students in your study group to review it.\n\nStudent: I didn't know about the peer review system. I'll definitely use that. One more question - when are your office hours? I might need more guidance.\n\nAdvisor: My office hours are Tuesday afternoon, from 2 to 4 pm. You're welcome to drop in, but I'd appreciate if you could book an appointment through the online system first, as it can get quite busy.\n\nStudent: Thank you so much, Dr. Roberts. I feel much clearer about what I need to do now.\n\nAdvisor: You're welcome, James. Good luck with it. Remember, the key is to start writing as soon as possible. Bye now.\n\nStudent: Goodbye.",
        "audioUrl": "https://www.soundhelix.com/examples/mp3/SoundHelix-Song-3.mp3",
        "context": "Conversation between two speakers - academic context",
        "type": "LISTENING",
        "skill": "listening",
        "subTasks": [
                  {
                    "type": "mcq",
                    "instruction": "Choose the correct answer",
                    "questions": [
                    {
                    "id": 21,
                    "text": "The student is studying",
                    "options": [
                      "Business",
                      "Computer Science",
                      "Engineering"
                    ],
                    "answer": "Business"
                  },
                  {
                  "id": 22,
                    "text": "What is the main concern about the assignment?",
                    "options": [
                      "the topic",
                      "the deadline",
                      "the length"
                    ],
                    "answer": "the deadline"
                  },
                  {
            "id": 23,
                    "text": "When is the assignment due?",
                    "options": [
                      "next week",
                      "in two weeks",
                      "in three weeks"
                    ],
                    "answer": "next week"
                  },
                  {
            "id": 24,
                    "text": "What does the advisor suggest about the research?",
                    "options": [
                      "visit the library",
                      "use online databases",
                      "interview professors"
                    ],
                    "answer": "use online databases"
                  },
                  {
            "id": 25,
                    "text": "How many sources are required for the bibliography?",
                    "options": [
                      "5",
                      "10",
                      "15"
                    ],
                    "answer": "15"
                  },
                  {
            "id": 26,
                    "text": "What format should the essay follow?",
                    "options": [
                      "APA",
                      "MLA",
                      "Harvard"
                    ],
                    "answer": "APA"
                  },
                  {
            "id": 27,
                    "text": "Who will review the first draft?",
                    "options": [
                      "the advisor",
                      "peer students",
                      "external examiner"
                    ],
                    "answer": "external examiner"          
                  }
          ]
         },
          {
            "type": "short-answer",
            "instruction": "Answer the questions below. Write NO MORE THAN TWO WORDS for each answer.",
            "questions": [
              {
                "id": 28,
                "text": "What is the minimum word count for the essay?",
                "answer": "3000 words",
                "wordLimit": 2,
                "allowNumber": true
              },
              {
                "id": 29,
                "text": "What software is recommended for formatting?",
                "answer": "Word",
                "wordLimit": 1,
                "allowNumber": false
              },
              {
                "id": 30,
                "text": "When are the office hours for the advisor?",
                "answer": "Tuesday afternoon",
                "wordLimit": 2,
                "allowNumber": false
              }
            ]
          }
        ]
      },
      {
        "id": "part4",
        "part": 4,
        "title": "Lecture on Animal Behavior",
        "subtitle": "Part 4: Listening",
        "description": "You will hear a lecture about animal behavior. First, you have some time to look at questions 31-40.",
        "transcript": "Professor: Good morning, everyone. Today I'd like to share with you the findings of our five-year research project on animal communication in the wild. This study was conducted across various ecosystems, and we examined over 30 different species to understand how animals communicate with each other.\n\nOur primary method was direct observation in natural habitats. We spent thousands of hours in the field, recording behaviors and analyzing patterns. What we found has truly remarkable implications for our understanding of animal intelligence.\n\nThe main finding of our research is that animals do indeed communicate with each other in complex ways. We documented over 200 distinct vocalizations across the species we studied. But it wasn't just about sounds - we also observed sophisticated body language and even chemical signaling in some species.\n\nOne of the most interesting discoveries was how animals use warning calls. For example, we found that predator presence triggers specific alarm calls in many species. These calls vary depending on the type of threat - whether it's a land predator or an aerial one. Some species even have different calls for different predators.\n\nWe were also surprised by the complexity of communication we observed. It wasn't just simple warnings or mating calls. Animals appear to be able to convey information about food sources, social hierarchies, and even emotional states. This complexity challenges our traditional view of animal cognition.\n\nLooking ahead, we're planning to examine social behavior in more detail. Our next phase will focus on how animals coordinate group activities and maintain social bonds. We want to understand the role of communication in group decision-making processes.\n\nThis research was made possible through government grants from the National Science Foundation. We also received support from several private donations, which helped fund our field research equipment.\n\nBefore I conclude, let me give you one more fascinating example: dolphins. They're known for their distinctive vocal calls, which they use for everything from locating each other to coordinating hunting activities. Each dolphin actually has its own unique signature whistle - essentially a name that other dolphins use to identify them.\n\nIn conclusion, our study demonstrates that animal communication is far more sophisticated than we previously thought. Thank you for your attention, and I'll be happy to take any questions.",
        "audioUrl": "https://www.soundhelix.com/examples/mp3/SoundHelix-Song-4.mp3",
        "context": "Monologue - educational talk",
        "type": "LISTENING",
        "skill": "listening",
        "subTasks": [
          {
            "type": "short-answer",
            "instruction": "Complete the notes below. Write NO MORE THAN TWO WORDS for each answer.",
            "questions": [
              {
                "id": 31,
                "text": "The study focuses on animal behavior in",
                "answer": "the wild",
                "wordLimit": 2,
                "allowNumber": false
              },
              {
                "id": 32,
                "text": "The main finding is that animals",
                "answer": "communicate",
                "wordLimit": 2,
                "allowNumber": false
              },
              {
                "id": 33,
                "text": "Future research will examine",
                "answer": "social behavior",
                "wordLimit": 2,
                "allowNumber": false
              },
              {
                "id": 34,
                "text": "The research was conducted over a period of",
                "answer": "five years",
                "wordLimit": 2,
                "allowNumber": true
              },
              {
                "id": 35,
                "text": "The main method used was",
                "answer": "observation",
                "wordLimit": 2,
                "allowNumber": false
              }
            ]
          },
          {
            "type": "mcq",
            "instruction": "Choose the correct answer",
            "questions": [
              {
                "id": 36,
                "text": "According to the lecture, what triggers the warning behavior?",
                "options": [
                  "food availability",
                  "predator presence",
                  "weather changes"
                ],
                "answer": "predator presence"
              },
              {
                "id": 37,
                "text": "How many species were studied in total?",
                "options": [
                  "12",
                  "25",
                  "30"
                ],
                "answer": "30"
              },
              {
                "id": 38,
                "text": "What was surprising about the results?",
                "options": [
                  "the complexity of communication",
                  "the speed of adaptation",
                  "the memory capacity"
                ],
                "answer": "the complexity of communication"
              },
              {
                "id": 39,
                "text": "The funding for the research came from",
                "options": [
                  "government grants",
                  "private donations",
                  "university funds"
                ],
                "answer": "government grants"
              }
            ]
          },
          {
            "type": "mcq",
            "instruction": "Answer",
            "questions": [
              {
                "id": 40,
                "text": "Dolphins are known for their ",
                "options": [
                  "vocal calls",
                  "body movements",
                  "chemical signals",
                  "electrical signals"
                ],
                "answer": "vocal calls"
              }
            ]
          }
        ]
      }
    ]
  }
}